rabit/__init__.py
rabit/cs.py
rabit/gif.py
rabit/rabit.py
rabit-0.3.dist-info/LICENSE
rabit-0.3.dist-info/METADATA
rabit-0.3.dist-info/WHEEL
rabit-0.3.dist-info/top_level.txt
rabit-0.3.dist-info/RECORD
