Metadata-Version: 2.1
Name: rabit
Version: 0.3
Summary: This project implements a simple API of turtle to draw line, rectangle, circle, text and convert the process into gif.
Home-page: http://github.com/ackeraa/rabit
Author: Acker
Author-email: acker2880@gmail.com
License: MIT
Platform: any
Requires-Python: >=3.6
Requires-Dist: pythonturtle
Requires-Dist: imageio
